README.md
setup.py
xiwal/__init__.py
xiwal/__main__.py
xiwal/image.py
xiwal/lch.py
xiwal/scheme.py
xiwal/term.py
xiwal.egg-info/PKG-INFO
xiwal.egg-info/SOURCES.txt
xiwal.egg-info/dependency_links.txt
xiwal.egg-info/entry_points.txt
xiwal.egg-info/top_level.txt