Metadata-Version: 1.0
Name: xiwal
Version: 0.0.0
Summary: Generate terminal color schemes
Home-page: https://github.com/xi/xiwal
Author: Tobias Bengfort
Author-email: tobias.bengfort@posteo.de
License: MIT
Platform: UNKNOWN
